{"name":"build-javascript","namedChunkGroups":{"polyfill":{"name":"polyfill","assets":[{"name":"webpack-runtime-1a06d0107b7506522dfd.js","size":6158},{"name":"polyfill-a6a9e8476add1045c345.js","size":85838}],"filteredAssets":0,"assetsSize":91996,"filteredAuxiliaryAssets":2,"auxiliaryAssetsSize":230045},"app":{"name":"app","assets":[{"name":"webpack-runtime-1a06d0107b7506522dfd.js","size":6158},{"name":"framework-f27b074ecebec0f1dbc4.js","size":128706},{"name":"app-9219071c395ef3fffffa.js","size":68949}],"filteredAssets":0,"assetsSize":203813,"filteredAuxiliaryAssets":3,"auxiliaryAssetsSize":606112},"component---src-pages-404-js":{"name":"component---src-pages-404-js","assets":[{"name":"styles.185c60bff5e3de477729.css","size":19685},{"name":"cb1608f2-9e50e4d4cfc99ce63bbb.js","size":2021},{"name":"a9a7754c-d1e0ec91a76ed49794d7.js","size":3207},{"name":"commons-f4084c557ecf72acf873.js","size":229604},{"name":"component---src-pages-404-js-c8d02a42709277099bc0.js","size":417}],"filteredAssets":0,"assetsSize":254934,"filteredAuxiliaryAssets":7,"auxiliaryAssetsSize":2628680},"component---src-pages-about-js":{"name":"component---src-pages-about-js","assets":[{"name":"styles.185c60bff5e3de477729.css","size":19685},{"name":"cb1608f2-9e50e4d4cfc99ce63bbb.js","size":2021},{"name":"a9a7754c-d1e0ec91a76ed49794d7.js","size":3207},{"name":"commons-f4084c557ecf72acf873.js","size":229604},{"name":"component---src-pages-about-js-839d876face1402d4ba3.js","size":4755}],"filteredAssets":0,"assetsSize":259272,"filteredAuxiliaryAssets":7,"auxiliaryAssetsSize":2636756},"component---src-pages-articles-mdx-slug-js":{"name":"component---src-pages-articles-mdx-slug-js","assets":[{"name":"styles.185c60bff5e3de477729.css","size":19685},{"name":"cb1608f2-9e50e4d4cfc99ce63bbb.js","size":2021},{"name":"a9a7754c-d1e0ec91a76ed49794d7.js","size":3207},{"name":"commons-f4084c557ecf72acf873.js","size":229604},{"name":"component---src-pages-articles-mdx-slug-js-9c9a4fa88739a7180ac1.js","size":14943}],"filteredAssets":0,"assetsSize":269460,"filteredAuxiliaryAssets":7,"auxiliaryAssetsSize":2680235},"component---src-pages-index-js":{"name":"component---src-pages-index-js","assets":[{"name":"styles.185c60bff5e3de477729.css","size":19685},{"name":"cb1608f2-9e50e4d4cfc99ce63bbb.js","size":2021},{"name":"a9a7754c-d1e0ec91a76ed49794d7.js","size":3207},{"name":"commons-f4084c557ecf72acf873.js","size":229604},{"name":"9951837d47d79f04e79aa5ff873796f9526ef842-b61811b85a74e7ee6e42.js","size":60454},{"name":"component---src-pages-index-js-6af5eadfed50129b939a.js","size":721}],"filteredAssets":0,"assetsSize":315692,"filteredAuxiliaryAssets":8,"auxiliaryAssetsSize":2870887},"component---src-pages-non-tech-js":{"name":"component---src-pages-non-tech-js","assets":[{"name":"styles.185c60bff5e3de477729.css","size":19685},{"name":"cb1608f2-9e50e4d4cfc99ce63bbb.js","size":2021},{"name":"a9a7754c-d1e0ec91a76ed49794d7.js","size":3207},{"name":"commons-f4084c557ecf72acf873.js","size":229604},{"name":"9951837d47d79f04e79aa5ff873796f9526ef842-b61811b85a74e7ee6e42.js","size":60454},{"name":"component---src-pages-non-tech-js-fff71251e6fc458a81be.js","size":724}],"filteredAssets":0,"assetsSize":315695,"filteredAuxiliaryAssets":8,"auxiliaryAssetsSize":2870891}},"assetsByChunkName":{"polyfill":["webpack-runtime-1a06d0107b7506522dfd.js","polyfill-a6a9e8476add1045c345.js"],"app":["webpack-runtime-1a06d0107b7506522dfd.js","framework-f27b074ecebec0f1dbc4.js","app-9219071c395ef3fffffa.js"],"component---src-pages-404-js":["styles.185c60bff5e3de477729.css","cb1608f2-9e50e4d4cfc99ce63bbb.js","a9a7754c-d1e0ec91a76ed49794d7.js","commons-f4084c557ecf72acf873.js","component---src-pages-404-js-c8d02a42709277099bc0.js"],"component---src-pages-about-js":["styles.185c60bff5e3de477729.css","cb1608f2-9e50e4d4cfc99ce63bbb.js","a9a7754c-d1e0ec91a76ed49794d7.js","commons-f4084c557ecf72acf873.js","component---src-pages-about-js-839d876face1402d4ba3.js"],"component---src-pages-articles-mdx-slug-js":["styles.185c60bff5e3de477729.css","cb1608f2-9e50e4d4cfc99ce63bbb.js","a9a7754c-d1e0ec91a76ed49794d7.js","commons-f4084c557ecf72acf873.js","component---src-pages-articles-mdx-slug-js-9c9a4fa88739a7180ac1.js"],"component---src-pages-index-js":["styles.185c60bff5e3de477729.css","cb1608f2-9e50e4d4cfc99ce63bbb.js","a9a7754c-d1e0ec91a76ed49794d7.js","commons-f4084c557ecf72acf873.js","9951837d47d79f04e79aa5ff873796f9526ef842-b61811b85a74e7ee6e42.js","component---src-pages-index-js-6af5eadfed50129b939a.js"],"component---src-pages-non-tech-js":["styles.185c60bff5e3de477729.css","cb1608f2-9e50e4d4cfc99ce63bbb.js","a9a7754c-d1e0ec91a76ed49794d7.js","commons-f4084c557ecf72acf873.js","9951837d47d79f04e79aa5ff873796f9526ef842-b61811b85a74e7ee6e42.js","component---src-pages-non-tech-js-fff71251e6fc458a81be.js"]},"childAssetsByChunkName":{}}